<?xml version="1.0" encoding="utf-8" ?>
<dwsync>
<file name="3A New Advertisement_Donation_Letter 2016.doc" server="107.180.46.225//httpdocs/" local="131197797600000000" remote="131197797600000000" Dst="2" />
<file name="3A New Advertisement_Donation_Letter 2017.doc" server="107.180.46.225//httpdocs/" local="131481608400000000" remote="131481608400000000" Dst="2" />
<file name="3B New Product_Donation_Letter 2016.doc" server="107.180.46.225//httpdocs/" local="131197797600000000" remote="131197797600000000" Dst="2" />
<file name="3B New Product_Donation_Letter 2017.doc" server="107.180.46.225//httpdocs/" local="131481608400000000" remote="131481608400000000" Dst="2" />
<file name="3C&D New Proclamation_Request and Template 2016.doc" server="107.180.46.225//httpdocs/" local="131197797600000000" remote="131197797600000000" Dst="2" />
<file name="3C&D New Proclamation_Request and Template 2017.doc" server="107.180.46.225//httpdocs/" local="131481608400000000" remote="131481608400000000" Dst="2" />
<file name="3E New Sample_Calendar_Listing 2016.doc" server="107.180.46.225//httpdocs/" local="131197797600000000" remote="131197797600000000" Dst="2" />
<file name="3E New Sample_Calendar_Listing 2017.doc" server="107.180.46.225//httpdocs/" local="131481608400000000" remote="131481608400000000" Dst="2" />
<file name="3F New Sample_Media_Pitch_Email 2016.doc" server="107.180.46.225//httpdocs/" local="131197797600000000" remote="131197797600000000" Dst="2" />
<file name="3F New Sample_Media_Pitch_Email 2017.doc" server="107.180.46.225//httpdocs/" local="131481608400000000" remote="131481608400000000" Dst="2" />
<file name="3G New Public_Service_Announcement 2016.doc" server="107.180.46.225//httpdocs/" local="131197797600000000" remote="131197797600000000" Dst="2" />
<file name="3G New Public_Service_Announcement 2017.doc" server="107.180.46.225//httpdocs/" local="131481608400000000" remote="131481608400000000" Dst="2" />
<file name="3H New Customizable_Press_Release 2016.doc" server="107.180.46.225//httpdocs/" local="131197797600000000" remote="131197797600000000" Dst="2" />
<file name="3H New Customizable_Press_Release 2017.doc" server="107.180.46.225//httpdocs/" local="131481608400000000" remote="131481608400000000" Dst="2" />
<file name="3I New Customizable_Media_Alert 2016.doc" server="107.180.46.225//httpdocs/" local="131197797600000000" remote="131197797600000000" Dst="2" />
<file name="3I New Customizable_Media_Alert 2017.doc" server="107.180.46.225//httpdocs/" local="131481608400000000" remote="131481608400000000" Dst="2" />
<file name="3M Adoptions Reporting Calendar 2016-2017.docx" server="107.180.46.225//httpdocs/" local="131201037000000000" remote="131201037000000000" Dst="2" />
<file name="3M Adoptions Reporting Calendar 2017-2018.docx" server="107.180.46.225//httpdocs/" local="131485450200000000" remote="131485450200000000" Dst="2" />
<file name="H4TH16-poster.pdf" server="107.180.46.225//httpdocs/" local="131201034000000000" remote="131201034000000000" Dst="2" />
<file name="H4TH17-poster.pdf" server="107.180.46.225//httpdocs/" local="131481820800000000" remote="131481820800000000" Dst="2" />
<file name="3A New Advertisement_Donation_Letter 2018.doc" server="107.180.46.225//httpdocs/" local="131817120680436581" remote="131817144000000000" Dst="2" />
<file name="3B New Product_Donation_Letter 2018.doc" server="107.180.46.225//httpdocs/" local="131817120682858376" remote="131817144000000000" Dst="2" />
<file name="3C&D New Proclamation_Request and Template 2018.doc" server="107.180.46.225//httpdocs/" local="131817120685146752" remote="131817144000000000" Dst="2" />
<file name="3E New Sample_Calendar_Listing 2018.doc" server="107.180.46.225//httpdocs/" local="131817120687508879" remote="131817144000000000" Dst="2" />
<file name="3F New Sample_Media_Pitch_Email 2018.doc" server="107.180.46.225//httpdocs/" local="131817120690033186" remote="131817144000000000" Dst="2" />
<file name="3G New Public_Service_Announcement 2018.doc" server="107.180.46.225//httpdocs/" local="131817120692540442" remote="131817144000000000" Dst="2" />
<file name="3H New Customizable_Press_Release 2018.doc" server="107.180.46.225//httpdocs/" local="131817120695060632" remote="131817144000000000" Dst="2" />
<file name="3I New Customizable_Media_Alert 2018.doc" server="107.180.46.225//httpdocs/" local="131817120697485850" remote="131817144000000000" Dst="2" />
<file name="3A New Advertisement_Donation_Letter 2019.doc" server="107.180.46.225//httpdocs/" local="132131632304539936" remote="132131691000000000" Dst="2" />
<file name="3B New Product_Donation_Letter 2019.doc" server="107.180.46.225//httpdocs/" local="132131632298059722" remote="132131691000000000" Dst="2" />
<file name="3C&D New Proclamation_Request and Template 2019.doc" server="107.180.46.225//httpdocs/" local="132131632298318884" remote="132131691000000000" Dst="2" />
<file name="3E Sample_Calendar_Listing 2019.doc" server="107.180.46.225//httpdocs/" local="132131632298568372" remote="132131691000000000" Dst="2" />
<file name="3F Sample_Media_Pitch_Email 2019.doc" server="107.180.46.225//httpdocs/" local="132131632298806163" remote="132131691000000000" Dst="2" />
<file name="3G Public_Service_Announcement 2018.doc" server="107.180.46.225//httpdocs/" local="132131632299025588" remote="132131691000000000" Dst="2" />
<file name="3H Customizable_Press_Release 2019.doc" server="107.180.46.225//httpdocs/" local="132131632299255313" remote="132131691000000000" Dst="2" />
<file name="3I Customizable_Media_Alert 2019.doc" server="107.180.46.225//httpdocs/" local="132131632299475290" remote="132131691000000000" Dst="2" />
<file name="3M Adoptions Reporting Calendar 2019-2020.docx" server="107.180.46.225//httpdocs/" local="132131632299790596" remote="132131691600000000" Dst="2" />
<file name="H4TH20-flyertemplate.pdf" server="107.180.46.225//httpdocs/" local="132460530169607201" remote="132466633200000000" Dst="2" />
<file name="H4TH20-poster.pdf" server="107.180.46.225//httpdocs/" local="132460530169451196" remote="132466633200000000" Dst="2" />
<file name="3M Adoptions Reporting Calendar 2020.docx" server="107.180.46.225//httpdocs/" local="132464833125870664" remote="132466633800000000" Dst="2" />
<file name="3F Sample_Media_Pitch_Email 2021.doc" server="107.180.46.225//httpdocs/" local="132756006326300000" remote="132756142800000000" Dst="2" />
<file name="3H Customizable_Press_Release 2021.doc" server="107.180.46.225//httpdocs/" local="132756007036330000" remote="132756143400000000" Dst="2" />
<file name="3M Adoptions Reporting Calendar 2021.docx" server="107.180.46.225//httpdocs/" local="132755283248320266" remote="132756143400000000" Dst="2" />
<file name="H4TH21-flyertemplate.pdf" server="107.180.46.225//httpdocs/" local="132460530169607201" remote="132756143400000000" Dst="2" />
<file name="H4TH21-poster.pdf" server="107.180.46.225//httpdocs/" local="132756165685886830" remote="132756166200000000" Dst="2" />
<file name="3I Customizable_Media_Alert 2021.doc" server="107.180.46.225//httpdocs/" local="132756007389910000" remote="132756145200000000" Dst="2" />
<file name="3A New Advertisement_Donation_Letter 2021.doc" server="107.180.46.225//httpdocs/" local="132775858776319657" remote="132775860000000000" Dst="2" />
<file name="3B New Product_Donation_Letter 2021.doc" server="107.180.46.225//httpdocs/" local="132775858846370305" remote="132775860000000000" Dst="2" />
<file name="3C&D New Proclamation_Request and Template 2021.doc" server="107.180.46.225//httpdocs/" local="132775858898213225" remote="132775860000000000" Dst="2" />
<file name="3E Sample_Calendar_Listing 2021.doc" server="107.180.46.225//httpdocs/" local="132775858962229790" remote="132775860000000000" Dst="2" />
</dwsync>